src/__init__.py
src/get_player_stats.py
nba_player_stats-0.0.1.dist-info/LICENSE
nba_player_stats-0.0.1.dist-info/METADATA
nba_player_stats-0.0.1.dist-info/WHEEL
nba_player_stats-0.0.1.dist-info/entry_points.txt
nba_player_stats-0.0.1.dist-info/top_level.txt
nba_player_stats-0.0.1.dist-info/RECORD
