Metadata-Version: 2.1
Name: nba-player-stats
Version: 0.0.1
Summary: View NBA player stats in the terminal
License-File: LICENSE
Requires-Dist: requests (>"2.28")
Requires-Dist: rich (>"12.5")
Requires-Dist: pandas (>"1.5")
Requires-Dist: lxml (>"4.8")
